vgraph_forge-0.1.2.dist-info/METADATA
vgraph_forge-0.1.2.dist-info/WHEEL
vgraph_forge-0.1.2.dist-info/licenses/LICENSE
vgraph_forge/__init__.py
vgraph_forge/vgraph_forge.pyd
vgraph_forge-0.1.2.dist-info/RECORD
