Metadata-Version: 2.4
Name: vgraph-forge
Version: 0.1.2
Classifier: Programming Language :: Python
Classifier: Programming Language :: Python :: 3
Classifier: Programming Language :: Rust
Classifier: License :: OSI Approved :: MIT License
Classifier: Operating System :: OS Independent
Requires-Dist: networkx>=3.0 ; extra == 'networkx'
Provides-Extra: networkx
License-File: LICENSE
Summary: A Rust-powered toolkit for building visibility graphs from time series.
Author-email: Julian Urrea <jurreaserna@gmail.com>
License: MIT
Requires-Python: >=3.9
